.bumpversion.cfg
LICENSE
MANIFEST.in
Makefile
README.md
pyproject.toml
requirements.txt
setup.py
examples/run_identity_chain.sh
examples/run_identity_chain_google.py
examples/run_identity_chain_huggingface.py
examples/run_identity_chain_openai.py
identitychain/__init__.py
identitychain/dialogue.py
identitychain/executor.py
identitychain/identity_chain.py
identitychain/utils.py
identitychain.egg-info/PKG-INFO
identitychain.egg-info/SOURCES.txt
identitychain.egg-info/dependency_links.txt
identitychain.egg-info/requires.txt
identitychain.egg-info/top_level.txt
identitychain/tests/test_executor.py
images/main.png
scripts/analyze_results.py
scripts/browse_results.py
scripts/reformat_EvalPlus.py
scripts/reformat_MBPP-S.py
scripts/run_tests.sh
scripts/human_judge/analyze_results_hj.py
scripts/human_judge/browse_samples.py
scripts/human_judge/compute_correlation.py