Metadata-Version: 2.1
Name: identitychain
Version: 0.1.0
Summary: Evaluation Framework for Code Large Language Models (Code LLMs)
Author-email: "marcusm117, Robin-Y-Ding" <authors@gmail.com>
License:                                  Apache License
Project-URL: repository, https://github.com/marcusm117/IdentityChain/
Classifier: Development Status :: 2 - Pre-Alpha
Classifier: Programming Language :: Python :: Implementation :: CPython
Classifier: Programming Language :: Python :: Implementation :: PyPy
Classifier: Programming Language :: Python :: 3
Classifier: Programming Language :: Python :: 3.10
Classifier: Programming Language :: Python :: 3.11
Classifier: Programming Language :: Python :: 3.12
Requires-Python: >=3.10
Provides-Extra: develop
License-File: LICENSE
